tecton_rift_extensions/__init__.py
tecton_rift_extensions/duckdb/httpfs.duckdb_extension
tecton_rift_extensions/duckdb/tecton.duckdb_extension
tecton_rift_extensions-1.2.0.dist-info/METADATA
tecton_rift_extensions-1.2.0.dist-info/WHEEL
tecton_rift_extensions-1.2.0.dist-info/top_level.txt
tecton_rift_extensions-1.2.0.dist-info/RECORD
