Metadata-Version: 2.1
Name: tecton-rift-extensions
Version: 1.2.0
Summary: DuckDB Extensions and Libraries for using Tecton Rift Compute Engine
Author-email: "Tecton, Inc." <support@tecton.ai>
License: Tecton Proprietary
Project-URL: Homepage, https://tecton.ai
Project-URL: Documentation, https://docs.tecton.ai
